kubedrctl/__init__.py
kubedrctl/cli/__init__.py
kubedrctl/cli/context.py
kubedrctl/cli/kubedrctl.py
kubedrctl/cli/commands/__init__.py
kubedrctl/cli/commands/cmd_list.py
kubedrctl/cli/commands/cmd_restore.py
kubedrctl/common/__init__.py
kubedrctl/common/util.py
kubedrctl-0.1.3.dist-info/LICENSE
kubedrctl-0.1.3.dist-info/METADATA
kubedrctl-0.1.3.dist-info/WHEEL
kubedrctl-0.1.3.dist-info/entry_points.txt
kubedrctl-0.1.3.dist-info/top_level.txt
kubedrctl-0.1.3.dist-info/RECORD
