Metadata-Version: 2.1
Name: kubedrctl
Version: 0.1.3
Summary: KubeDR CLI.
Home-page: https://github.com/catalogicsoftware/kubedrctl
Author: Catalogic Software, Inc.
Author-email: raghu@catalogicsoftware.com
License: Apache License 2.0
Keywords: development
Platform: UNKNOWN
Classifier: Development Status :: 4 - Beta
Classifier: Intended Audience :: Developers
Classifier: Topic :: Software Development
Classifier: License :: OSI Approved :: Apache Software License
Classifier: Programming Language :: Python :: 3
Classifier: Programming Language :: Python :: 3.6
Requires-Dist: click
Provides-Extra: dev
Requires-Dist: check-manifest ; extra == 'dev'
Provides-Extra: test
Requires-Dist: coverage ; extra == 'test'
